omlmd/__init__.py
omlmd/cli.py
omlmd/constants.py
omlmd/helpers.py
omlmd/listener.py
omlmd/model_metadata.py
omlmd/provider.py
omlmd-0.1.6.dist-info/LICENSE
omlmd-0.1.6.dist-info/METADATA
omlmd-0.1.6.dist-info/WHEEL
omlmd-0.1.6.dist-info/entry_points.txt
omlmd-0.1.6.dist-info/RECORD
