Metadata-Version: 2.1
Name: omlmd
Version: 0.1.6
Summary: OCI Artifact for ML model & metadata
Author: Matteo Mortari
Author-email: matteo.mortari@gmail.com
Requires-Python: >=3.9,<4.0
Classifier: Programming Language :: Python :: 3
Classifier: Programming Language :: Python :: 3.9
Classifier: Programming Language :: Python :: 3.10
Classifier: Programming Language :: Python :: 3.11
Classifier: Programming Language :: Python :: 3.12
Classifier: Programming Language :: Python :: 3.13
Requires-Dist: click (>=8.1.7,<9.0.0)
Requires-Dist: cloup (>=3.0.5,<4.0.0)
Requires-Dist: oras (>=0.2.22,<0.3.0)
Requires-Dist: pyyaml (>=6.0.1,<7.0.0)
Project-URL: Changelog, https://github.com/containers/omlmd/releases
Project-URL: Documentation, https://containers.github.io/omlmd
Project-URL: Homepage, https://containers.github.io/omlmd
Project-URL: Issues, https://github.com/containers/omlmd/issues
Project-URL: Repository, https://github.com/containers/omlmd
